{"cameraMode":{"drawMode":0,"name":"Shaded","section":"Shading Mode"},"sceneLighting":true,"audioPlay":false,"sceneViewState":{"m_AlwaysRefresh":false,"showFog":true,"showSkybox":true,"showFlares":true,"showImageEffects":true,"showParticleSystems":true,"showVisualEffectGraphs":true,"m_FxEnabled":true},"in2DMode":false,"pivot":{"x":1.6205387115478516,"y":2.589561700820923,"z":6.448474884033203},"rotation":{"x":0.025172097608447076,"y":0.03508000448346138,"z":0.0008895633509382606,"w":-0.9990776181221008},"size":6.299123287200928,"orthographic":false}